machine_engine_python/__init__.py
machine_engine_python/cli.py
machine_engine_python/machine_engine_python.py
machine_engine_python-0.1.0.dist-info/DESCRIPTION.rst
machine_engine_python-0.1.0.dist-info/METADATA
machine_engine_python-0.1.0.dist-info/RECORD
machine_engine_python-0.1.0.dist-info/WHEEL
machine_engine_python-0.1.0.dist-info/entry_points.txt
machine_engine_python-0.1.0.dist-info/metadata.json
machine_engine_python-0.1.0.dist-info/top_level.txt
