Metadata-Version: 2.0
Name: machine-engine-python
Version: 0.1.0
Summary: machine engine client package for python projects
Home-page: https://github.com/IRiViI/machine_engine_python
Author: Hendrik Willem Vink
Author-email: rckvnk@gmail.com
License: MIT license
Keywords: machine_engine_python
Platform: UNKNOWN
Classifier: Development Status :: 2 - Pre-Alpha
Classifier: Intended Audience :: Developers
Classifier: License :: OSI Approved :: MIT License
Classifier: Natural Language :: English
Classifier: Programming Language :: Python :: 2
Classifier: Programming Language :: Python :: 2.6
Classifier: Programming Language :: Python :: 2.7
Classifier: Programming Language :: Python :: 3
Classifier: Programming Language :: Python :: 3.3
Classifier: Programming Language :: Python :: 3.4
Classifier: Programming Language :: Python :: 3.5
Requires-Dist: Click (>=6.0)
